accelbyte_py_sdk/api/loginqueue/__init__.py
accelbyte_py_sdk/api/loginqueue/errors.py
accelbyte_py_sdk/api/loginqueue/models/__init__.py
accelbyte_py_sdk/api/loginqueue/models/apimodels_configuration_request.py
accelbyte_py_sdk/api/loginqueue/models/apimodels_configuration_response.py
accelbyte_py_sdk/api/loginqueue/models/apimodels_link.py
accelbyte_py_sdk/api/loginqueue/models/apimodels_queue_status_response.py
accelbyte_py_sdk/api/loginqueue/models/apimodels_refresh_ticket_response.py
accelbyte_py_sdk/api/loginqueue/models/response_error.py
accelbyte_py_sdk/api/loginqueue/operations/__init__.py
accelbyte_py_sdk/api/loginqueue/operations/admin_v1/__init__.py
accelbyte_py_sdk/api/loginqueue/operations/admin_v1/admin_get_configuration.py
accelbyte_py_sdk/api/loginqueue/operations/admin_v1/admin_get_status.py
accelbyte_py_sdk/api/loginqueue/operations/admin_v1/admin_update_configuration.py
accelbyte_py_sdk/api/loginqueue/operations/ticket_v1/__init__.py
accelbyte_py_sdk/api/loginqueue/operations/ticket_v1/cancel_ticket.py
accelbyte_py_sdk/api/loginqueue/operations/ticket_v1/refresh_ticket.py
accelbyte_py_sdk/api/loginqueue/wrappers/__init__.py
accelbyte_py_sdk/api/loginqueue/wrappers/_admin_v1.py
accelbyte_py_sdk/api/loginqueue/wrappers/_ticket_v1.py
accelbyte_py_sdk_service_loginqueue-2.0.6.dist-info/METADATA
accelbyte_py_sdk_service_loginqueue-2.0.6.dist-info/WHEEL
accelbyte_py_sdk_service_loginqueue-2.0.6.dist-info/top_level.txt
accelbyte_py_sdk_service_loginqueue-2.0.6.dist-info/RECORD
