Metadata-Version: 2.4
Name: accelbyte-py-sdk-service-loginqueue
Version: 2.0.6
Summary: AccelByte Python SDK - AccelByte Gaming Services Login Queue Service
Requires-Python: >=3.9
Requires-Dist: accelbyte-py-sdk-core
